{"cameraMode":{"drawMode":0,"name":"Shaded","section":"Shading Mode"},"sceneLighting":false,"audioPlay":false,"sceneViewState":{"m_AlwaysRefresh":false,"showFog":true,"showSkybox":false,"showFlares":true,"showImageEffects":true,"showParticleSystems":true,"showVisualEffectGraphs":true,"m_FxEnabled":true},"in2DMode":false,"pivot":{"x":0.0,"y":0.3499999940395355,"z":149.8000030517578},"rotation":{"x":-0.0069225868210196499,"y":0.940377950668335,"z":-0.33986616134643557,"w":-0.01890561170876026},"size":0.6062213182449341,"orthographic":false}